haramss_lotto/__init__.py
haramss_lotto/lotto.py
HaramSs_lotto-0.2.0.dist-info/METADATA
HaramSs_lotto-0.2.0.dist-info/WHEEL
HaramSs_lotto-0.2.0.dist-info/entry_points.txt
HaramSs_lotto-0.2.0.dist-info/top_level.txt
HaramSs_lotto-0.2.0.dist-info/RECORD
