Metadata-Version: 2.1
Name: HaramSs_lotto
Version: 0.2.0
Summary: Default template for PDM package
Author-email: HaramSs <haram8274@gmail.com>
License: MIT
Requires-Python: >=3.9
